<xml>
	<template name="ST[15,19] Packet Stores Status Report" l="576" h="770">
		<item type="Repeater" x="120" y="30" data_type="uint16" data_size="2" data_mask="0xffff" data_shift="0" >
			<subitem type="TextBox" name="textStoreName" text="-" x="70" y="5" l="110" h="20" data_type="str" data_size="0f" data_mask="-1" data_shift="0" id="false" />	
			<subitem type="Label" name="labelStoreName" text="Store " x="12" y="2" l="60" h="13" data_type=""/>	
			<subitem type="CheckBox" name="checkboxStoreStatus" text="Enabled " x="200" y="0" l="80" h="20" data_type="uint8" data_size="1" data_mask="0x01" data_shift="0"/>	
			<subitem type="CheckBox" name="checkboxStoreRetrieval" text="Retrieval Enable " x="280" y="0" l="120" h="20" data_type="uint8" data_size="1" data_mask="0x01" data_shift="0"/>	
			<subitem type="CheckBox" name="checkboxTimeRange" text="Time Range Enable "  x="400" y="0" l="130" h="20" data_type="uint8" data_size="1" data_mask="0x01" data_shift="0"/>	
		</item>		
	</template>			
</xml>

